easyvoice/__init__.py
easyvoice-0.2.0.dist-info/licenses/LICENSE
easyvoice-0.2.0.dist-info/METADATA
easyvoice-0.2.0.dist-info/WHEEL
easyvoice-0.2.0.dist-info/top_level.txt
easyvoice-0.2.0.dist-info/RECORD
