Metadata-Version: 2.4
Name: easyvoice
Version: 0.2.0
Summary: Simple NLP, TTS, and ASR library
Author-email: Yuras <mix1122@gmail.com>
License: MIT
Requires-Python: >=3.7
License-File: LICENSE
Requires-Dist: nltk
Requires-Dist: gTTS
Requires-Dist: SpeechRecognition
Requires-Dist: pydub
Dynamic: license-file
